caimira/__init__.py
caimira/api/__init__.py
caimira/api/app.py
caimira/api/controller/__init__.py
caimira/api/controller/co2_report_controller.py
caimira/api/controller/virus_report_controller.py
caimira/api/routes/__init__.py
caimira/api/routes/base_handler.py
caimira/api/routes/landing_routes.py
caimira/api/routes/report_routes.py
caimira/api/routes/routes.py
caimira/calculator/__init__.py
caimira/calculator/models/__init__.py
caimira/calculator/models/dataclass_utils.py
caimira/calculator/models/enums.py
caimira/calculator/models/models.py
caimira/calculator/models/profiler.py
caimira/calculator/models/utils.py
caimira/calculator/models/data/__init__.py
caimira/calculator/models/data/global_weather_set.json
caimira/calculator/models/data/hadisd_station_fullinfo_v311_202001p.txt
caimira/calculator/models/data/weather.py
caimira/calculator/models/monte_carlo/__init__.py
caimira/calculator/models/monte_carlo/__init__.pyi
caimira/calculator/models/monte_carlo/data.py
caimira/calculator/models/monte_carlo/models.py
caimira/calculator/models/monte_carlo/sampleable.py
caimira/calculator/report/__init__.py
caimira/calculator/report/co2_report_data.py
caimira/calculator/report/virus_report_data.py
caimira/calculator/store/data_registry.py
caimira/calculator/store/data_service.py
caimira/calculator/validators/__init__.py
caimira/calculator/validators/defaults.py
caimira/calculator/validators/form_validator.py
caimira/calculator/validators/co2/__init__.py
caimira/calculator/validators/co2/co2_validator.py
caimira/calculator/validators/virus/__init__.py
caimira/calculator/validators/virus/virus_validator.py
caimira/scripts/data/vaccine_effectiveness.py
caimira-4.17.8.dist-info/LICENSE
caimira-4.17.8.dist-info/METADATA
caimira-4.17.8.dist-info/WHEEL
caimira-4.17.8.dist-info/top_level.txt
caimira-4.17.8.dist-info/RECORD
